{
  "project_info": {
    "project_number": "222473625001",
    "project_id": "pc-api-7068476234413575643-558",
    "storage_bucket": "pc-api-7068476234413575643-558.appspot.com"
  },
  "client": [
    {
      "client_info": {
        "mobilesdk_app_id": "1:222473625001:android:2cfdb3925dad04a02db8b8",
        "android_client_info": {
          "package_name": "com.alientodevida.app"
        }
      },
      "oauth_client": [
        {
          "client_id": "222473625001-gvibrt10g18h2082pg491tj14bmubej1.apps.googleusercontent.com",
          "client_type": 3
        }
      ],
      "api_key": [
        {
          "current_key": "AIzaSyCET4nRtGkbpsJFsZfZzKVKw6et5TmAT6Y"
        }
      ],
      "services": {
        "appinvite_service": {
          "other_platform_oauth_client": [
            {
              "client_id": "222473625001-gvibrt10g18h2082pg491tj14bmubej1.apps.googleusercontent.com",
              "client_type": 3
            }
          ]
        }
      }
    }
  ],
  "configuration_version": "1"
}